dsPyLib/__init__.py
dsPyLib/ali/__init__.py
dsPyLib/ali/ali_access_token.py
dsPyLib/ali/ali_tts.py
dsPyLib/db/__init__.py
dsPyLib/db/pgsql.py
dsPyLib/holiday/__init__.py
dsPyLib/holiday/holiday.py
dsPyLib/pandas/__init__.py
dsPyLib/pandas/data_frame.py
dsPyLib/pandas/date_frame.py
dsPyLib/pandas/pandas_config.py
dsPyLib/peewee/__init__.py
dsPyLib/peewee/db_base_model.py
dsPyLib/peewee/db_mgr.py
dsPyLib/res/__init__.py
dsPyLib/res/notice.wav
dsPyLib/sound/__init__.py
dsPyLib/sound/sound.py
dsPyLib/test/__init__.py
dsPyLib/test/decorator_elapsed.py
dsPyLib/test/decorator_schedule.py
dsPyLib/test/decorator_timer.py
dsPyLib/utils/__init__.py
dsPyLib/utils/datetime.py
dsPyLib/utils/decorator.py
dsPyLib/utils/logging.py
dsPyLib/utils/misc.py
dsPyLib/utils/scheduler.py
dsPyLib/utils/style.py
dsPyLib/utils/timez.py
dsPyLib-0.0.28.dist-info/LICENSE
dsPyLib-0.0.28.dist-info/METADATA
dsPyLib-0.0.28.dist-info/WHEEL
dsPyLib-0.0.28.dist-info/top_level.txt
dsPyLib-0.0.28.dist-info/zip-safe
dsPyLib-0.0.28.dist-info/RECORD
