Metadata-Version: 2.1
Name: dsPyLib
Version: 0.0.28
Summary: A common python library for DS.
Home-page: https://github.com/dragonsun7/dsPyLib
Author: Dragon Sun
Author-email: dragonsun7@163.com
License: MIT
Keywords: dsPyLib
Platform: UNKNOWN
Classifier: Programming Language :: Python :: 3
Classifier: License :: OSI Approved :: MIT License
Classifier: Operating System :: OS Independent
Requires-Dist: psycopg2-binary
Requires-Dist: python-dateutil
Requires-Dist: pandas
Requires-Dist: pyaudio
Requires-Dist: peewee
